cpropep_build.py
pypropep/__init__.py
pypropep/equilibrium.py
pypropep/error.py
pypropep/performance.py
pypropep/propellant.py
pypropep/cpropep/__init__.py
pypropep/cpropep/_cpropep.so
pypropep/data/propellant.dat
pypropep/data/thermo.dat
pypropep-0.1.1.dist-info/DESCRIPTION.rst
pypropep-0.1.1.dist-info/METADATA
pypropep-0.1.1.dist-info/RECORD
pypropep-0.1.1.dist-info/WHEEL
pypropep-0.1.1.dist-info/metadata.json
pypropep-0.1.1.dist-info/top_level.txt
