Metadata-Version: 2.0
Name: pypropep
Version: 0.1.1
Summary: Python wrapper for cpropep rocket performance tool
Home-page: https://github.com/jonnydyer/pypropep
Author: Jonny Dyer
Author-email: jonny.dyer@gmail.com
License: GPLv3
Platform: UNKNOWN
Requires-Dist: attrdict
Requires-Dist: cffi (>=1.0.0)
